README
nosegoat.py
setup.py
NoseGoat.egg-info/PKG-INFO
NoseGoat.egg-info/SOURCES.txt
NoseGoat.egg-info/dependency_links.txt
NoseGoat.egg-info/entry_points.txt
NoseGoat.egg-info/requires.txt
NoseGoat.egg-info/top_level.txt