Metadata-Version: 1.0
Name: NoseGoat
Version: 0.1
Summary: Use the goat Luke!
Home-page: https://github.com/mattharrison/NoseGoat
Author: Matt Harrison
Author-email: matthewharrison@gmail.com
License: PSF
Platform: goats eat anything
